README.rst
setup.py
abstrys/__init__.py
abstrys/sphinx_xwiki_builder.py
abstrys/sphinx_xwiki_writer.py
sphinx_xwiki_builder.egg-info/PKG-INFO
sphinx_xwiki_builder.egg-info/SOURCES.txt
sphinx_xwiki_builder.egg-info/dependency_links.txt
sphinx_xwiki_builder.egg-info/requires.txt
sphinx_xwiki_builder.egg-info/top_level.txt
test/test-snake2camel.py