Metadata-Version: 1.1
Name: sphinx-xwiki-builder
Version: 0.1.1
Summary: Builds Sphinx documentation source to XWiki-syntax output
Home-page: https://github.com/Abstrys/sphinx-wiki-builder/
Author: Eron Hennessey
Author-email: eron@abstrys.com
License: MIT
Keywords: sphinx builder xwiki
Platform: UNKNOWN
Classifier: Development Status :: 3 - Alpha
Classifier: Topic :: Utilities
Classifier: License :: OSI Approved :: MIT License
